perturbator/__init__.py
perturbator/commands/__init__.py
perturbator/commands/delete_element.py
perturbator/commands/delete_process_fragment.py
perturbator/commands/execute_from_file.py
perturbator/commands/generate_new_element.py
perturbator/commands/insert_element.py
perturbator/commands/insert_process_fragment_conditional.py
perturbator/commands/insert_process_fragment_parallel.py
perturbator/commands/insert_process_fragment_serial.py
perturbator/language_parser/__init__.py
perturbator/language_parser/grammar.tx
perturbator/language_parser/language_model_generator.py
perturbator/perturbator.py
perturbator/support_modules/__init__.py
perturbator/support_modules/perturbator.py
perturbator-0.1.23.dist-info/entry_points.txt
perturbator-0.1.23.dist-info/LICENSE
perturbator-0.1.23.dist-info/WHEEL
perturbator-0.1.23.dist-info/METADATA
perturbator-0.1.23.dist-info/RECORD
