Metadata-Version: 2.1
Name: perturbator
Version: 0.1.23
Summary: Tool to apply change patterns on Business Process Models
License: MIT
Author: Zohaib Ahmed Butt
Author-email: zohaibahmedbutt@gmail.com
Requires-Python: >=3.8,<3.9
Classifier: License :: OSI Approved :: MIT License
Classifier: Programming Language :: Python :: 3
Classifier: Programming Language :: Python :: 3.8
Requires-Dist: arrow (>=1.0.3,<2.0.0)
Requires-Dist: click (>=7.1.2,<8.0.0)
Requires-Dist: shortuuid (>=1.0.1,<2.0.0)
Requires-Dist: textX (>=2.3.0,<3.0.0)
